hardwarextractor/__init__.py
hardwarextractor/__main__.py
hardwarextractor/_version.py
hardwarextractor/cli_engine.py
hardwarextractor/aggregate/__init__.py
hardwarextractor/aggregate/aggregator.py
hardwarextractor/app/__init__.py
hardwarextractor/app/config.py
hardwarextractor/app/orchestrator.py
hardwarextractor/app/paths.py
hardwarextractor/cache/__init__.py
hardwarextractor/cache/sqlite_cache.py
hardwarextractor/classifier/__init__.py
hardwarextractor/classifier/heuristic.py
hardwarextractor/cli/__init__.py
hardwarextractor/cli/interactive.py
hardwarextractor/cli/renderer.py
hardwarextractor/core/__init__.py
hardwarextractor/core/events.py
hardwarextractor/core/feedback.py
hardwarextractor/core/github_reporter.py
hardwarextractor/core/logger.py
hardwarextractor/core/source_chain.py
hardwarextractor/core/updater.py
hardwarextractor/data/__init__.py
hardwarextractor/data/catalog.py
hardwarextractor/data/reference_urls.py
hardwarextractor/data/resolver_catalog.py
hardwarextractor/engine/__init__.py
hardwarextractor/engine/commands.py
hardwarextractor/engine/ficha_manager.py
hardwarextractor/engine/ipc.py
hardwarextractor/export/__init__.py
hardwarextractor/export/base.py
hardwarextractor/export/csv_exporter.py
hardwarextractor/export/factory.py
hardwarextractor/export/md_exporter.py
hardwarextractor/export/xlsx_exporter.py
hardwarextractor/mapper/__init__.py
hardwarextractor/mapper/mapper.py
hardwarextractor/models/__init__.py
hardwarextractor/models/schemas.py
hardwarextractor/normalize/__init__.py
hardwarextractor/normalize/input.py
hardwarextractor/resolver/__init__.py
hardwarextractor/resolver/catalog.py
hardwarextractor/resolver/resolver.py
hardwarextractor/resolver/url_resolver.py
hardwarextractor/scrape/__init__.py
hardwarextractor/scrape/extractors.py
hardwarextractor/scrape/jsonld.py
hardwarextractor/scrape/mappings.py
hardwarextractor/scrape/parse_utils.py
hardwarextractor/scrape/service.py
hardwarextractor/scrape/spiders.py
hardwarextractor-0.2.2.dist-info/licenses/LICENSE
hardwarextractor-0.2.2.dist-info/METADATA
hardwarextractor-0.2.2.dist-info/WHEEL
hardwarextractor-0.2.2.dist-info/entry_points.txt
hardwarextractor-0.2.2.dist-info/top_level.txt
hardwarextractor-0.2.2.dist-info/RECORD
