Metadata-Version: 2.4
Name: hardwarextractor
Version: 0.2.2
Summary: HardwareXtractor - Extraccion de specs de hardware con trazabilidad
License-Expression: MIT
Requires-Python: >=3.11
License-File: LICENSE
Requires-Dist: scrapy>=2.11.0
Requires-Dist: parsel>=1.9.1
Requires-Dist: requests>=2.32.0
Provides-Extra: browser
Requires-Dist: playwright>=1.40.0; extra == "browser"
Provides-Extra: excel
Requires-Dist: openpyxl>=3.1.0; extra == "excel"
Provides-Extra: full
Requires-Dist: playwright>=1.40.0; extra == "full"
Requires-Dist: openpyxl>=3.1.0; extra == "full"
Provides-Extra: dev
Requires-Dist: pytest>=7.0.0; extra == "dev"
Requires-Dist: pytest-cov>=4.0.0; extra == "dev"
Requires-Dist: pytest-asyncio>=0.21.0; extra == "dev"
Dynamic: license-file
